{"11":"{\"bookingId\":11,\"customerId\":1,\"startingPoint\":\"B\",\"destinationPoint\":\"E\",\"time\":\"9.00AM\",\"charges\":450,\"bookingType\":true,\"taxi\":\"Taxi-1\"}","12":"{\"bookingId\":12,\"customerId\":1,\"startingPoint\":\"D\",\"destinationPoint\":\"A\",\"time\":\"5.00PM\",\"charges\":450,\"bookingType\":true,\"taxi\":\"Taxi-3\"}","13":"{\"bookingId\":13,\"customerId\":1,\"startingPoint\":\"B\",\"destinationPoint\":\"E\",\"time\":\"5.00AM\",\"charges\":450,\"bookingType\":true,\"taxi\":\"Taxi-3\"}","14":"{\"bookingId\":14,\"customerId\":1,\"startingPoint\":\"A\",\"destinationPoint\":\"E\",\"time\":\"6.00PM\",\"charges\":600,\"bookingType\":true,\"taxi\":\"Taxi-2\"}","1":"{\"bookingId\":1,\"customerId\":1,\"startingPoint\":\"A\",\"destinationPoint\":\"D\",\"time\":\"6.00AM\",\"charges\":180,\"bookingType\":false,\"taxi\":\"Taxi-1\"}","2":"{\"bookingId\":2,\"customerId\":1,\"startingPoint\":\"A\",\"destinationPoint\":\"C\",\"time\":\"6.00AM\",\"charges\":300,\"bookingType\":true,\"taxi\":\"Taxi-2\"}","3":"{\"bookingId\":3,\"customerId\":1,\"startingPoint\":\"A\",\"destinationPoint\":\"E\",\"time\":\"5.00AM\",\"charges\":240,\"bookingType\":false,\"taxi\":\"Taxi-3\"}","4":"{\"bookingId\":4,\"customerId\":1,\"startingPoint\":\"A\",\"destinationPoint\":\"B\",\"time\":\"5.00AM\",\"charges\":150,\"bookingType\":true,\"taxi\":\"Taxi-4\"}","5":"{\"bookingId\":5,\"customerId\":1,\"startingPoint\":\"A\",\"destinationPoint\":\"D\",\"time\":\"8.00AM\",\"charges\":450,\"bookingType\":true,\"taxi\":\"Taxi-5\"}","6":"{\"bookingId\":6,\"customerId\":1,\"startingPoint\":\"B\",\"destinationPoint\":\"D\",\"time\":\"5.00AM\",\"charges\":300,\"bookingType\":true,\"taxi\":\"Taxi-4\"}","7":"{\"bookingId\":7,\"customerId\":1,\"startingPoint\":\"A\",\"destinationPoint\":\"C\",\"time\":\"5.25PM\",\"charges\":300,\"bookingType\":true,\"taxi\":\"Taxi-2\"}","8":"{\"bookingId\":8,\"customerId\":1,\"startingPoint\":\"A\",\"destinationPoint\":\"D\",\"time\":\"5.00PM\",\"charges\":180,\"bookingType\":false,\"taxi\":\"Taxi-2\"}","9":"{\"bookingId\":9,\"customerId\":1,\"startingPoint\":\"E\",\"destinationPoint\":\"D\",\"time\":\"5.00am\",\"charges\":150,\"bookingType\":true,\"taxi\":\"Taxi-3\"}","10":"{\"bookingId\":10,\"customerId\":1,\"startingPoint\":\"C\",\"destinationPoint\":\"A\",\"time\":\"6.00AM\",\"charges\":300,\"bookingType\":true,\"taxi\":\"Taxi-1\"}"}